wxyz/json_e/__init__.py
wxyz/json_e/_version.py
wxyz/json_e/base.py
wxyz/json_e/install.json
wxyz/json_e/widget_jsone.py
wxyz/json_e/js/LICENSE.txt
wxyz/json_e/js/README.md
wxyz/json_e/js/package.json
wxyz/json_e/labextension/package.json
wxyz/json_e/labextension/static/333.1bd0eeafd8f9e2e48e93.js
wxyz/json_e/labextension/static/511.01bd5067979490ffb125.js
wxyz/json_e/labextension/static/559.107ac19a61b1b33e1eb3.js
wxyz/json_e/labextension/static/568.9e4ba75e8f29a8227aae.js
wxyz/json_e/labextension/static/704.0c3848c207b66b2b66f2.js
wxyz/json_e/labextension/static/760.c1c5568bc421c06bf08d.js
wxyz/json_e/labextension/static/remoteEntry.3d22c90813aabe87e7cb.js
wxyz/json_e/labextension/static/style.js
wxyz_json_e-0.5.1.data/data/share/jupyter/labextensions/@deathbeds/wxyz-json-e/install.json
wxyz_json_e-0.5.1.data/data/share/jupyter/labextensions/@deathbeds/wxyz-json-e/package.json
wxyz_json_e-0.5.1.data/data/share/jupyter/labextensions/@deathbeds/wxyz-json-e/static/333.1bd0eeafd8f9e2e48e93.js
wxyz_json_e-0.5.1.data/data/share/jupyter/labextensions/@deathbeds/wxyz-json-e/static/511.01bd5067979490ffb125.js
wxyz_json_e-0.5.1.data/data/share/jupyter/labextensions/@deathbeds/wxyz-json-e/static/559.107ac19a61b1b33e1eb3.js
wxyz_json_e-0.5.1.data/data/share/jupyter/labextensions/@deathbeds/wxyz-json-e/static/568.9e4ba75e8f29a8227aae.js
wxyz_json_e-0.5.1.data/data/share/jupyter/labextensions/@deathbeds/wxyz-json-e/static/704.0c3848c207b66b2b66f2.js
wxyz_json_e-0.5.1.data/data/share/jupyter/labextensions/@deathbeds/wxyz-json-e/static/760.c1c5568bc421c06bf08d.js
wxyz_json_e-0.5.1.data/data/share/jupyter/labextensions/@deathbeds/wxyz-json-e/static/remoteEntry.3d22c90813aabe87e7cb.js
wxyz_json_e-0.5.1.data/data/share/jupyter/labextensions/@deathbeds/wxyz-json-e/static/style.js
wxyz_json_e-0.5.1.dist-info/LICENSE.txt
wxyz_json_e-0.5.1.dist-info/METADATA
wxyz_json_e-0.5.1.dist-info/WHEEL
wxyz_json_e-0.5.1.dist-info/top_level.txt
wxyz_json_e-0.5.1.dist-info/RECORD
